{
  "generatedAtBJT": "2026-03-30 21:47:25",
  "rangeHours": 36,
  "count": 101,
  "items": [
    {
      "source": "YahooFinance-Markets",
      "headline": "Stock market today: Dow, S&P 500, Nasdaq rise entering shortened week featuring jobs data, war uncertainty",
      "summary": "",
      "url": "https://finance.yahoo.com/news/live/stock-market-today-dow-sp-500-nasdaq-rise-entering-shortened-week-featuring-jobs-data-war-uncertainty-230645176.html",
      "datetime": 1774878445,
      "related": "RSS"
    },
    {
      "source": "YahooFinance-Markets",
      "headline": "Prediction: If the Iran Conflict Escalates, These Energy Stocks Could Double in 2026",
      "summary": "",
      "url": "https://finance.yahoo.com/sectors/energy/articles/prediction-iran-conflict-escalates-energy-133500357.html",
      "datetime": 1774878445,
      "related": "RSS"
    },
    {
      "source": "YahooFinance-Markets",
      "headline": "Starbucks investors reelect full board, rejecting labor-backed challenge",
      "summary": "",
      "url": "https://finance.yahoo.com/news/starbucks-investors-reelect-full-board-133416698.html",
      "datetime": 1774878445,
      "related": "RSS"
    },
    {
      "source": "YahooFinance-Markets",
      "headline": "Is Caterpillar (CAT) The Best Data Center Stock in Bill Gates’ Latest Portfolio?",
      "summary": "",
      "url": "https://finance.yahoo.com/markets/stocks/articles/caterpillar-cat-best-data-center-133349628.html",
      "datetime": 1774878445,
      "related": "RSS"
    },
    {
      "source": "YahooFinance-Markets",
      "headline": "Eli Lilly and Company (LLY) Continued to Gain from Its Incretin Portfolio",
      "summary": "",
      "url": "https://finance.yahoo.com/sectors/healthcare/articles/eli-lilly-company-lly-continued-133154499.html",
      "datetime": 1774878445,
      "related": "RSS"
    },
    {
      "source": "YahooFinance-Markets",
      "headline": "Bill Gates’ Latest Portfolio: Is FedEx (FDX) The Best Stock to Buy?",
      "summary": "",
      "url": "https://finance.yahoo.com/markets/stocks/articles/bill-gates-latest-portfolio-fedex-132344819.html",
      "datetime": 1774878445,
      "related": "RSS"
    },
    {
      "source": "YahooFinance-Markets",
      "headline": "High gas prices, Iran war take huge toll on U.S. consumer confidence",
      "summary": "",
      "url": "https://finance.yahoo.com/economy/articles/high-gas-prices-iran-war-133300283.html",
      "datetime": 1774878445,
      "related": "RSS"
    },
    {
      "source": "YahooFinance-Markets",
      "headline": "Negative Sentiment Around Insurance-Related Companies Pressured Arthur J Gallagher (AJG)",
      "summary": "",
      "url": "https://finance.yahoo.com/markets/stocks/articles/negative-sentiment-around-insurance-related-132037724.html",
      "datetime": 1774878445,
      "related": "RSS"
    },
    {
      "source": "YahooFinance-Markets",
      "headline": "Stock market bulls, don't forget this one: Oil price shocks usually lead to a recession",
      "summary": "",
      "url": "https://finance.yahoo.com/news/stock-market-bulls-dont-forget-this-one-oil-price-shocks-usually-lead-to-a-recession-131921062.html",
      "datetime": 1774878445,
      "related": "RSS"
    },
    {
      "source": "YahooFinance-Markets",
      "headline": "Spotify (SPOT) Fell Due to Concerns Around Pricing Actions",
      "summary": "",
      "url": "https://finance.yahoo.com/markets/stocks/articles/spotify-spot-fell-due-concerns-131857674.html",
      "datetime": 1774878445,
      "related": "RSS"
    },
    {
      "source": "YahooFinance-Markets",
      "headline": "What Makes Keysight Technologies (KEYS) a Defensive Opportunity in AI Infrastructure Build-Out?",
      "summary": "",
      "url": "https://finance.yahoo.com/markets/stocks/articles/makes-keysight-technologies-keys-defensive-131617928.html",
      "datetime": 1774878445,
      "related": "RSS"
    },
    {
      "source": "YahooFinance-Markets",
      "headline": "Tax Day is coming. Avoid these common IRS filing mistakes.",
      "summary": "",
      "url": "https://finance.yahoo.com/economy/policy/articles/tax-day-coming-avoid-common-132835807.html",
      "datetime": 1774878445,
      "related": "RSS"
    },
    {
      "source": "YahooFinance-Markets",
      "headline": "United Therapeutics Soars As Study Results Bring 'New Era'",
      "summary": "",
      "url": "https://www.investors.com/news/united-therapeutics-stock-tyvaso-ipf-phase-3-study/?src=A00220&yptr=yahoo",
      "datetime": 1774878445,
      "related": "RSS"
    },
    {
      "source": "YahooFinance-Markets",
      "headline": "Here’s Why Uber (UBER) Fell Despite Reporting Strong Results and Healthy Free Cash Flow",
      "summary": "",
      "url": "https://finance.yahoo.com/markets/stocks/articles/why-uber-uber-fell-despite-131259914.html",
      "datetime": 1774878445,
      "related": "RSS"
    },
    {
      "source": "YahooFinance-Markets",
      "headline": "Is Coca-Cola Femsa (KOF) The Best Defensive Stock to Buy Amid Middle East War?",
      "summary": "",
      "url": "https://finance.yahoo.com/markets/stocks/articles/coca-cola-femsa-kof-best-131145079.html",
      "datetime": 1774878445,
      "related": "RSS"
    },
    {
      "source": "YahooFinance-Markets",
      "headline": "Stock Market Today: Dow Rises On U.S.-Iran News; Powell Comments Up Next (Live Coverage)",
      "summary": "",
      "url": "https://www.investors.com/market-trend/stock-market-today/dow-jones-sp500-nasdaq-us-iran-war-news-powell/?src=A00220&yptr=yahoo",
      "datetime": 1774878445,
      "related": "RSS"
    },
    {
      "source": "YahooFinance-Markets",
      "headline": "One Analyst Sees Microsoft Soaring 90%. Here’s What the Market Might Be Missing",
      "summary": "",
      "url": "https://finance.yahoo.com/markets/stocks/articles/one-analyst-sees-microsoft-soaring-132729778.html",
      "datetime": 1774878445,
      "related": "RSS"
    },
    {
      "source": "YahooFinance-Markets",
      "headline": "Meta Named Morgan Stanley's New Top Pick Following Sell-Off",
      "summary": "",
      "url": "https://www.investors.com/news/technology/meta-stock-ai-morgan-stanley/?src=A00220&yptr=yahoo",
      "datetime": 1774878445,
      "related": "RSS"
    },
    {
      "source": "YahooFinance-Markets",
      "headline": "2 'Magnificent 7' stocks see stunning plunges",
      "summary": "",
      "url": "https://finance.yahoo.com/news/2-magnificent-7-stocks-see-stunning-plunges-130430799.html",
      "datetime": 1774878445,
      "related": "RSS"
    },
    {
      "source": "YahooFinance-Markets",
      "headline": "Strategy Appears To Have Paused Its Bitcoin Purchases",
      "summary": "",
      "url": "https://finance.yahoo.com/markets/crypto/articles/strategy-appears-paused-bitcoin-purchases-130200847.html",
      "datetime": 1774878445,
      "related": "RSS"
    },
    {
      "source": "YahooFinance-Markets",
      "headline": "Bitcoin Price Rebounds From Month Low, These Two Miners Form Bases",
      "summary": "",
      "url": "https://www.investors.com/news/bitcoin-price-rebound-miners-basing-terawulf-hut8-cathie-wood-ark-invest-bullish/?src=A00220&yptr=yahoo",
      "datetime": 1774878445,
      "related": "RSS"
    },
    {
      "source": "YahooFinance-Markets",
      "headline": "Aluminum Is the New Oil. These Stocks Are Soaring.",
      "summary": "",
      "url": "https://www.barrons.com/articles/alcoa-stock-aluminum-iran-war-trump-d7571bd4?siteid=yhoof2&yptr=yahoo",
      "datetime": 1774878445,
      "related": "RSS"
    },
    {
      "source": "YahooFinance-Markets",
      "headline": "Strong Demand Lifted Taiwan Semiconductor Manufacturing Company Limited (TSM) Higher in Q4",
      "summary": "",
      "url": "https://finance.yahoo.com/markets/stocks/articles/strong-demand-lifted-taiwan-semiconductor-130106361.html",
      "datetime": 1774878445,
      "related": "RSS"
    },
    {
      "source": "YahooFinance-Markets",
      "headline": "FBI shuts down 3 India-based call centers posing as Social Security, tied to $50M stolen from Americans. How they worked",
      "summary": "",
      "url": "https://finance.yahoo.com/economy/policy/articles/fbi-shuts-down-3-india-130100119.html",
      "datetime": 1774878445,
      "related": "RSS"
    },
    {
      "source": "YahooFinance-Markets",
      "headline": "Tax refunds up nearly 11%, with over 37 Million Americans cashing in on new tax breaks",
      "summary": "",
      "url": "https://finance.yahoo.com/personal-finance/taxes/article/tax-refunds-up-nearly-11-with-over-37-million-americans-cashing-in-on-new-tax-breaks-202713045.html",
      "datetime": 1774878445,
      "related": "RSS"
    },
    {
      "source": "YahooFinance-Markets",
      "headline": "Selling crypto? What to know before you cash out.",
      "summary": "",
      "url": "https://finance.yahoo.com/personal-finance/investing/article/how-to-sell-crypto-130000431.html",
      "datetime": 1774878445,
      "related": "RSS"
    },
    {
      "source": "YahooFinance-Markets",
      "headline": "3 Dividend Stocks You Can Buy Today and Forget About for the Next 20 Years",
      "summary": "",
      "url": "https://finance.yahoo.com/markets/stocks/articles/3-dividend-stocks-buy-today-132652335.html",
      "datetime": 1774878445,
      "related": "RSS"
    },
    {
      "source": "YahooFinance-Markets",
      "headline": "Taiwan Semiconductor Manufacturing Co. (TSM) is Benefiting from Strong Underlying Business Growth",
      "summary": "",
      "url": "https://finance.yahoo.com/markets/stocks/articles/taiwan-semiconductor-manufacturing-co-tsm-125604873.html",
      "datetime": 1774878445,
      "related": "RSS"
    },
    {
      "source": "YahooFinance-Markets",
      "headline": "Tech stocks today: Big Tech stocks look to recover from bruising week, Mistral AI raises $830 million",
      "summary": "",
      "url": "https://finance.yahoo.com/news/live/tech-stocks-today-big-tech-stocks-look-to-recover-from-bruising-week-mistral-ai-raises-830-million-144220032.html",
      "datetime": 1774878445,
      "related": "RSS"
    },
    {
      "source": "YahooFinance-Markets",
      "headline": "Here’s Why Sequoia Strategy Believes Capital One Financial (COF) is Trading at an Attractive Valuation",
      "summary": "",
      "url": "https://finance.yahoo.com/markets/stocks/articles/why-sequoia-strategy-believes-capital-125017312.html",
      "datetime": 1774878445,
      "related": "RSS"
    },
    {
      "source": "YahooFinance-Markets",
      "headline": "Sequoia Strategy’s Updates on Formula One Group (FWONK)",
      "summary": "",
      "url": "https://finance.yahoo.com/markets/stocks/articles/sequoia-strategy-updates-formula-one-124730407.html",
      "datetime": 1774878445,
      "related": "RSS"
    },
    {
      "source": "YahooFinance-Markets",
      "headline": "Nasdaq Correction: 3 Growth Stocks That Make for Screaming Buys Right Now",
      "summary": "",
      "url": "https://finance.yahoo.com/markets/stocks/articles/nasdaq-correction-3-growth-stocks-132600509.html",
      "datetime": 1774878445,
      "related": "RSS"
    },
    {
      "source": "YahooFinance-Markets",
      "headline": "Hyperscale Data Expands Michigan AI Footprint With 48.5 Acre Acquisition",
      "summary": "",
      "url": "https://finance.yahoo.com/sectors/technology/articles/hyperscale-data-expands-michigan-ai-124600591.html",
      "datetime": 1774878445,
      "related": "RSS"
    },
    {
      "source": "YahooFinance-Markets",
      "headline": "What Makes The Charles Schwab Corporation (SCHW) a Leader in Wealth Management Growth?",
      "summary": "",
      "url": "https://finance.yahoo.com/markets/stocks/articles/makes-charles-schwab-corporation-schw-124423415.html",
      "datetime": 1774878445,
      "related": "RSS"
    },
    {
      "source": "YahooFinance-Markets",
      "headline": "BYD Raises Forecasts For Overseas Sales",
      "summary": "",
      "url": "https://www.investors.com/news/byd-exports-tesla-china-evs-electric-vehicles-autos-cars/?src=A00220&yptr=yahoo",
      "datetime": 1774878445,
      "related": "RSS"
    },
    {
      "source": "YahooFinance-Markets",
      "headline": "5 ways retirees are earning extra income from home without a full-time job",
      "summary": "",
      "url": "https://finance.yahoo.com/markets/articles/5-ways-retirees-earning-extra-123000289.html",
      "datetime": 1774878445,
      "related": "RSS"
    },
    {
      "source": "YahooFinance-Markets",
      "headline": "Coinbase Rises 3%, Bitmine Jumps 4%: Is the Crypto Rally Back?",
      "summary": "",
      "url": "https://finance.yahoo.com/markets/crypto/articles/coinbase-rises-3-bitmine-jumps-132255734.html",
      "datetime": 1774878445,
      "related": "RSS"
    },
    {
      "source": "YahooFinance-Markets",
      "headline": "What Makes Simpson Manufacturing Co. (SSD) an Investment Bet?",
      "summary": "",
      "url": "https://finance.yahoo.com/markets/stocks/articles/makes-simpson-manufacturing-co-ssd-122817574.html",
      "datetime": 1774878445,
      "related": "RSS"
    },
    {
      "source": "YahooFinance-Markets",
      "headline": "Is Ecolab (ECL) The Best Under-The-Radar AI Stock to Buy Now?",
      "summary": "",
      "url": "https://finance.yahoo.com/markets/stocks/articles/ecolab-ecl-best-under-radar-122347319.html",
      "datetime": 1774878445,
      "related": "RSS"
    },
    {
      "source": "YahooFinance-Markets",
      "headline": "Can Wix.com (WIX) Benefit from the Proliferation of AI Adoption?",
      "summary": "",
      "url": "https://finance.yahoo.com/markets/stocks/articles/wix-com-wix-benefit-proliferation-121121904.html",
      "datetime": 1774878445,
      "related": "RSS"
    },
    {
      "source": "YahooFinance-Markets",
      "headline": "Is Caterpillar Inc. (CAT) A Good Stock To Buy Now?",
      "summary": "",
      "url": "https://finance.yahoo.com/markets/stocks/articles/caterpillar-inc-cat-good-stock-120621026.html",
      "datetime": 1774878445,
      "related": "RSS"
    },
    {
      "source": "YahooFinance-Markets",
      "headline": "The Low-Cost ETF to Buy Now That Gold Is Above $5,500 Again",
      "summary": "",
      "url": "https://finance.yahoo.com/markets/commodities/articles/low-cost-etf-buy-now-131742140.html",
      "datetime": 1774878445,
      "related": "RSS"
    },
    {
      "source": "YahooFinance-Markets",
      "headline": "Bitcoin and ethereum price today, Monday, March 30, 2026: Values moving up after lower weekend prices",
      "summary": "",
      "url": "https://finance.yahoo.com/personal-finance/investing/article/bitcoin-and-ethereum-price-today-monday-march-30-2026-values-moving-up-after-lower-weekend-prices-120045377.html",
      "datetime": 1774878445,
      "related": "RSS"
    },
    {
      "source": "YahooFinance-Markets",
      "headline": "How to invest in silver: A beginner's guide",
      "summary": "",
      "url": "https://finance.yahoo.com/personal-finance/investing/article/how-to-invest-in-silver-for-beginners-120000199.html",
      "datetime": 1774878445,
      "related": "RSS"
    },
    {
      "source": "YahooFinance-Markets",
      "headline": "Freight bankruptcies mount in March as trucking, logistics firms file Chapter 11",
      "summary": "",
      "url": "https://finance.yahoo.com/economy/articles/freight-bankruptcies-mount-march-trucking-120000643.html",
      "datetime": 1774878445,
      "related": "RSS"
    },
    {
      "source": "YahooFinance-Markets",
      "headline": "Gold price today, Monday, March 30: Gold holds strong, opening above $4,500",
      "summary": "",
      "url": "https://finance.yahoo.com/personal-finance/investing/article/gold-price-today-monday-march-30-gold-holds-strong-opening-above-4500-111116970.html",
      "datetime": 1774878445,
      "related": "RSS"
    },
    {
      "source": "YahooFinance-Markets",
      "headline": "Here’s What a ‘Small’ Side Hustle Can Do to Your Taxes — and How To Prepare",
      "summary": "",
      "url": "https://finance.yahoo.com/economy/policy/articles/small-side-hustle-taxes-prepare-131711326.html",
      "datetime": 1774878445,
      "related": "RSS"
    },
    {
      "source": "YahooFinance-Markets",
      "headline": "Best CD rates today, March 30, 2026 (Lock in up to 4.15% APY)",
      "summary": "",
      "url": "https://finance.yahoo.com/personal-finance/banking/article/copy-best-cd-rates-today-monday-march-30-2026-100000258.html",
      "datetime": 1774878445,
      "related": "RSS"
    },
    {
      "source": "YahooFinance-Markets",
      "headline": "Best money market account rates today, March 30, 2026 (Earn up to 4.01% APY)",
      "summary": "",
      "url": "https://finance.yahoo.com/personal-finance/banking/article/copy-best-money-market-account-rates-today-monday-march-30-2026-100000781.html",
      "datetime": 1774878445,
      "related": "RSS"
    },
    {
      "source": "YahooFinance-Markets",
      "headline": "HELOC and home equity loan rates Monday, March 30, 2026: How to tap home equity for a low-interest loan",
      "summary": "",
      "url": "https://finance.yahoo.com/personal-finance/mortgages/article/heloc-home-equity-loan-rates-today-monday-march-30-2026-100000389.html",
      "datetime": 1774878445,
      "related": "RSS"
    },
    {
      "source": "Investing-Markets",
      "headline": "China’s BYD confident of reaching 1.5 million unit overseas sales in 2026",
      "summary": "",
      "url": "https://www.investing.com/news/stock-market-news/chinas-byd-confident-of-reaching-15-million-unit-overseas-sales-in-2026-4588186",
      "datetime": 1774878445,
      "related": "RSS"
    },
    {
      "source": "Investing-Markets",
      "headline": "Air Canada CEO Michael Rousseau to retire after French flub",
      "summary": "",
      "url": "https://www.investing.com/news/stock-market-news/air-canada-ceo-michael-rousseau-to-retire-4587745",
      "datetime": 1774878445,
      "related": "RSS"
    },
    {
      "source": "Investing-Markets",
      "headline": "US Department of Labor issues 401k guidelines on private assets",
      "summary": "",
      "url": "https://www.investing.com/news/stock-market-news/us-department-of-labor-issues-401k-guidelines-on-private-assets-4588182",
      "datetime": 1774878445,
      "related": "RSS"
    },
    {
      "source": "Investing-Markets",
      "headline": "Uber acquires chauffeur service Blacklane in bid to expand luxury rides",
      "summary": "",
      "url": "https://www.investing.com/news/stock-market-news/uber-acquires-chauffeur-service-blacklane-in-bid-to-expand-luxury-rides-4588172",
      "datetime": 1774878445,
      "related": "RSS"
    },
    {
      "source": "Investing-Markets",
      "headline": "Wall Street opens higher after selloff, Middle East in focus",
      "summary": "",
      "url": "https://www.investing.com/news/stock-market-news/wall-street-opens-higher-after-selloff-middle-east-in-focus-4588168",
      "datetime": 1774878445,
      "related": "RSS"
    },
    {
      "source": "Investing-Markets",
      "headline": "Alaska Air signals bigger first-quarter loss as fuel costs surge",
      "summary": "",
      "url": "https://www.investing.com/news/stock-market-news/alaska-air-signals-bigger-firstquarter-loss-as-fuel-costs-surge-4588071",
      "datetime": 1774878445,
      "related": "RSS"
    },
    {
      "source": "Investing-Markets",
      "headline": "Starbucks investors reelect full board, rejecting labor-backed challenge",
      "summary": "",
      "url": "https://www.investing.com/news/stock-market-news/starbucks-investors-reelect-full-board-rejecting-laborbacked-challenge-4588165",
      "datetime": 1774878445,
      "related": "RSS"
    },
    {
      "source": "Investing-Markets",
      "headline": "GM to increase heavy-duty truck production, WSJ reports",
      "summary": "",
      "url": "https://www.investing.com/news/stock-market-news/gm-to-increase-heavyduty-truck-production-wsj-reports-4588163",
      "datetime": 1774878445,
      "related": "RSS"
    },
    {
      "source": "Investing-Markets",
      "headline": "Up 65%+ in March, this German energy stock is surging - and it’s not the only one",
      "summary": "",
      "url": "https://www.investing.com/news/stock-market-news/up-65-in-march-this-german-energy-stock-is-surging--and-its-not-the-only-one-4588087",
      "datetime": 1774878445,
      "related": "RSS"
    },
    {
      "source": "Investing-Markets",
      "headline": "Stocks rebound from last week, open higher as Trump touts ’serious’ Iran talks",
      "summary": "",
      "url": "https://www.investing.com/news/stock-market-news/us-stock-futures-fall-as-iran-fears-persist-trump-comments-offer-some-relief-4586647",
      "datetime": 1774878445,
      "related": "RSS"
    },
    {
      "source": "CNBC-Top",
      "headline": "Department of Labor proposes rules for including alternative assets in 401(k)s",
      "summary": "The Department of Labor has proposed rules regarding how plan sponsors and fiduciaries can include alternative assets in 401(k) retirement accounts.",
      "url": "https://www.cnbc.com/2026/03/30/401ks-alternative-investments.html",
      "datetime": 1774878409,
      "related": "RSS"
    },
    {
      "source": "MarketWatch-Top",
      "headline": "Gold’s bull run could be nearing its finish line, says UBS strategist",
      "summary": "Bullion prices may fall if the Federal Reserve decides to hold interest rates for the rest of the year, which the market has priced in.",
      "url": "https://www.marketwatch.com/story/golds-bull-run-could-be-nearing-its-finish-line-says-ubs-strategist-0f2d94f8?mod=mw_rss_topstories",
      "datetime": 1774878240,
      "related": "RSS"
    },
    {
      "source": "CNBC-World",
      "headline": "Treasury yields move lower as investors look to jobs data",
      "summary": "U.S. Treasury yields were lower on Friday as investors looked ahead to job data for the week and monitored the U.S.-Iran war, which entered its fifth week.",
      "url": "https://www.cnbc.com/2026/03/30/us-treasury-yields-investors-look-ahead-to-busy-week-of-jobs-data.html",
      "datetime": 1774878020,
      "related": "RSS"
    },
    {
      "source": "MarketWatch-Top",
      "headline": "The market’s wobble amid Iran war has left world-beating U.S. stocks ‘extremely cheap,’ says Bill Ackman",
      "summary": "Ignore the bears, says the hedge-fund billionaire",
      "url": "https://www.marketwatch.com/story/the-markets-iran-war-wobble-has-left-world-beating-u-s-stocks-extremely-cheap-says-bill-ackman-6d135e49?mod=mw_rss_topstories",
      "datetime": 1774877460,
      "related": "RSS"
    },
    {
      "source": "CNBC-Top",
      "headline": "Trump says U.S. will destroy Iran’s oil wells, Kharg Island without deal to 'immediately' reopen Hormuz Strait",
      "summary": "Donald Trump warned the U.S. will completely obliterate all of Iran's electric generating plants, oil wells and Kharg Island if a peace deal is not reached.",
      "url": "https://www.cnbc.com/2026/03/30/trump-iran-war-obliterate-kharg-island-strait-of-hormuz-peace-deal.html",
      "datetime": 1774876852,
      "related": "RSS"
    },
    {
      "source": "MarketWatch-Top",
      "headline": "‘I was shoveling sidewalks at 8 years old’: I’m a 73-year-old boomer dad with two kids. Here’s what I teach them about finance",
      "summary": "“My parents knew nothing about finance and investing, so my buddies and I had to figure it out on our own.”",
      "url": "https://www.marketwatch.com/story/i-was-shoveling-sidewalks-at-8-years-old-im-a-73-year-old-boomer-dad-with-two-kids-heres-what-i-teach-them-about-finance-339e1295?mod=mw_rss_topstories",
      "datetime": 1774876680,
      "related": "RSS"
    },
    {
      "source": "CNBC-Top",
      "headline": "Trump reportedly wants to 'take the oil in Iran' as Tehran targets water, power facilities in Kuwait",
      "summary": "The Middle East conflict has entered its fifth week, with attacks expanding across the region and raising risks to energy and infrastructure.",
      "url": "https://www.cnbc.com/2026/03/30/trump-iran-oil-middle-east-war-israel-us-kuwait-attack-.html",
      "datetime": 1774876050,
      "related": "RSS"
    },
    {
      "source": "CNBC-Top",
      "headline": "Russia welcomes arrival of oil tanker in Cuba after Trump softens approach to U.S. blockade",
      "summary": "A Russian oil tanker carrying a humanitarian shipment of 100,000 tons of crude oil reportedly arrived in Cuba on Monday.",
      "url": "https://www.cnbc.com/2026/03/30/cuba-crisis-trump-fuel-oil-bloackade-energy-russia-tanker-tariffs.html",
      "datetime": 1774875856,
      "related": "RSS"
    },
    {
      "source": "CNBC-Top",
      "headline": "The Iran war is defense tech's chance to shine, but few systems and weapons are ready",
      "summary": "Palmer Luckey's Anduril, software AI company Palantir and Elon Musk's SpaceX are getting the lion's share of defense tech dollars from the Pentagon.",
      "url": "https://www.cnbc.com/2026/03/28/iran-war-defense-tech-drones-trump-hegseth.html",
      "datetime": 1774875755,
      "related": "RSS"
    },
    {
      "source": "CNBC-Top",
      "headline": "Samsung-backed AI chip firm Rebellions raises $400 million ahead of IPO",
      "summary": "Rebellions' chips are focused on AI inferencing, putting it in competition with Nvidia as well as other startups from Groq to Cerebras.",
      "url": "https://www.cnbc.com/2026/03/30/ai-chip-startup-rebellions-raises-400-million-ipo.html",
      "datetime": 1774875601,
      "related": "RSS"
    },
    {
      "source": "CNBC-Top",
      "headline": "We're exiting this tech stock to replenish our cash pile after our annual charity donation",
      "summary": "Our annual distribution to charity took our cash levels from roughly 15% to 6.5%.",
      "url": "https://www.cnbc.com/2026/03/30/were-exiting-this-tech-stock-to-replenish-our-cash-pile-after-our-annual-charity-donation.html",
      "datetime": 1774875465,
      "related": "RSS"
    },
    {
      "source": "MarketWatch-Top",
      "headline": "Oil prices jump after Trump says he could ‘blow up’ Iran’s power plants, oil wells and Kharg Island if deal not reached",
      "summary": "Crude prices jumped early Monday as uncertainty over an endgame for the war increases",
      "url": "https://www.marketwatch.com/story/oil-prices-head-towards-highest-close-in-four-years-as-iran-conflict-shows-no-sign-of-ending-af9a093c?mod=mw_rss_topstories",
      "datetime": 1774874700,
      "related": "RSS"
    },
    {
      "source": "CNBC-Top",
      "headline": "Nearly 1 in 3 car buyers are underwater on trade-ins — analyst calls dollar amount 'troubling'",
      "summary": "An estimated 30.5% of car buyers with a trade-in owe more than it's worth, up 4.2 percentage points from a year ago but still below the prepandemic share.",
      "url": "https://www.cnbc.com/2026/03/30/negative-equity-trade-ins-car-buyers.html",
      "datetime": 1774873906,
      "related": "RSS"
    },
    {
      "source": "CNBC-Tech",
      "headline": "Oil's record month, TSA pay, the Pokémon card resale market and more in Morning Squawk",
      "summary": "Here are five key things investors need to know to start the trading day.",
      "url": "https://www.cnbc.com/2026/03/30/5-things-to-know-before-the-market-opens.html",
      "datetime": 1774873228,
      "related": "RSS"
    },
    {
      "source": "MarketWatch-Top",
      "headline": "My PayPal account received money from the Philippines with two phone numbers listed. I called them. Big mistake.",
      "summary": "“I know my information is on the dark web, and I have taken steps to be cautious.”",
      "url": "https://www.marketwatch.com/story/my-paypal-account-received-money-from-the-philippines-with-two-phone-numbers-listed-i-called-them-big-mistake-5cd4cd47?mod=mw_rss_topstories",
      "datetime": 1774872540,
      "related": "RSS"
    },
    {
      "source": "CNBC-Top",
      "headline": "Oil prices rise with Brent heading for record monthly surge as Iran war enters fifth week",
      "summary": "Oil prices climbed on Monday after Yemen's Houthis said they had fired missiles at Israel, opening a new front in the U.S.- and Israeli-led conflict with Iran.",
      "url": "https://www.cnbc.com/2026/03/30/oil-price-today-wti-brent-yemen-houthis-israel-iran-war.html",
      "datetime": 1774872496,
      "related": "RSS"
    },
    {
      "source": "CNBC-Top",
      "headline": "Pessimism sets in for Europe as Iran war hits economic and consumer confidence",
      "summary": "Economic sentiment in Europe plummeted in March, according to the latest flash data released on Monday.",
      "url": "https://www.cnbc.com/2026/03/30/european-economic-sentiment-consumer-confidence-march-iran-war-trump.html",
      "datetime": 1774872203,
      "related": "RSS"
    },
    {
      "source": "CNBC-Top",
      "headline": "New fees, fewer flights: Higher fuel prices pinch consumer budgets beyond the gas pump",
      "summary": "As corporate policies change, Americans will feel higher oil prices in their wallets beyond the gas pump.",
      "url": "https://www.cnbc.com/2026/03/28/oil-doordash-lyft-usps-united.html",
      "datetime": 1774872047,
      "related": "RSS"
    },
    {
      "source": "MarketWatch-Top",
      "headline": "Sysco goes all in on the ‘cash and carry’ food-service business with a $29 billion buyout",
      "summary": "Sysco’s stock falls after announcing a $29.1 billion cash-and-stock deal to buy Jetro Restaurant Depot.",
      "url": "https://www.marketwatch.com/story/sysco-goes-all-in-on-the-cash-and-carry-food-service-business-with-a-29-billion-buyout-5e06c72c?mod=mw_rss_topstories",
      "datetime": 1774872000,
      "related": "RSS"
    },
    {
      "source": "MarketWatch-Top",
      "headline": "The S&P 500’s correction is ‘getting closer to its ending,’ says Morgan Stanley’s Mike Wilson",
      "summary": "Here’s what makes this cycle different than others that saw oil prices spike.",
      "url": "https://www.marketwatch.com/story/the-s-p-500s-correction-is-getting-closer-to-its-ending-says-morgan-stanleys-mike-wilson-82d97caf?mod=mw_rss_topstories",
      "datetime": 1774870920,
      "related": "RSS"
    },
    {
      "source": "CNBC-Top",
      "headline": "European markets rise as Iran war intensifies and economic sentiment sours",
      "summary": "European stocks started the new trading week in positive territory though the war in Iran showed no signs of ending soon, entering its fifth week.",
      "url": "https://www.cnbc.com/2026/03/30/european-markets-stoxx-600-ftse-dax-cac-iran-news-oil-prices.html",
      "datetime": 1774870286,
      "related": "RSS"
    },
    {
      "source": "CNBC-Top",
      "headline": "Quantum technology firms race to market as the industry sees ‘inflection point’",
      "summary": "Quantum technology firms are braving turbulent markets to publicly list this year, as the nascent industry looks towards commercialization.",
      "url": "https://www.cnbc.com/2026/03/30/quantum-computing-firms-go-public-breakthroughs-commercialization.html",
      "datetime": 1774870155,
      "related": "RSS"
    },
    {
      "source": "MarketWatch-Top",
      "headline": "German arms manufacturer in damage-control mode as stock slumps after PR disaster",
      "summary": "Rheinmetall’s CEO has been criticized after making derisive remarks about Ukraine’s low-cost and highly efficient drone technology.",
      "url": "https://www.marketwatch.com/story/german-arms-manufacturer-in-damage-control-mode-after-pr-disaster-and-stock-slump-bf377456?mod=mw_rss_topstories",
      "datetime": 1774867260,
      "related": "RSS"
    },
    {
      "source": "MarketWatch-Top",
      "headline": "‘Several hurricanes have come close’: I’m 73 and live in a mobile home in Florida. Do I ditch my $2,400 home insurance?",
      "summary": "“I live in a 2016 double-wide mobile home with no mortgage.”",
      "url": "https://www.marketwatch.com/story/several-hurricanes-have-come-close-im-73-and-live-in-a-mobile-home-in-florida-do-i-ditch-my-2-400-home-insurance-87397157?mod=mw_rss_topstories",
      "datetime": 1774865880,
      "related": "RSS"
    },
    {
      "source": "CNBC-World",
      "headline": "Beijing's surprise intervention on Meta's Manus rattles tech founders, VCs eyeing 'China shedding'",
      "summary": "Beijing's review has fueled concerns and confusion among Chinese tech founders and investors that had quietly embraced the so-called \"Singapore-washing\" model.",
      "url": "https://www.cnbc.com/2026/03/27/meta-manus-china-review-singapore-washing-model-regulation-.html",
      "datetime": 1774863371,
      "related": "RSS"
    },
    {
      "source": "MarketWatch-Top",
      "headline": "‘She has taken my inheritance’: My mom bullied my grandmother to change her will and physically abused her. What can we do?",
      "summary": "“I believe my mom caused her physical injury and abused her on multiple occasions.”",
      "url": "https://www.marketwatch.com/story/she-has-taken-my-inheritance-my-mom-bullied-my-grandmother-to-change-her-will-and-physically-abused-her-what-can-we-do-2c4ee13f?mod=mw_rss_topstories",
      "datetime": 1774863240,
      "related": "RSS"
    },
    {
      "source": "CNBC-Top",
      "headline": "Mistral secures $830 million in debt financing to fund AI data center",
      "summary": "Mistral is one of the few European startups building foundational AI models.",
      "url": "https://www.cnbc.com/2026/03/30/mistral-ai-paris-data-center-cluster-debt-financing.html",
      "datetime": 1774856100,
      "related": "RSS"
    },
    {
      "source": "CNBC-World",
      "headline": "South Korea's Kospi leads declines in Asia as Middle East war enters fifth week",
      "summary": "Asia-Pacific markets fell Monday as the Middle East war enters its fifth week.",
      "url": "https://www.cnbc.com/2026/03/30/asia-pacific-markets-nikkei-225-kospi-hang-seng-index-oil.html",
      "datetime": 1774855171,
      "related": "RSS"
    },
    {
      "source": "CNBC-Top",
      "headline": "Budget airlines built on cheap fares now face a painful reality: Fuel is getting expensive",
      "summary": "Budget airlines try to maintain low costs while fuel costs continue to rise",
      "url": "https://www.cnbc.com/2026/03/30/asia-budget-airlines-fuel-costs-middle-east-routes-demand.html",
      "datetime": 1774852140,
      "related": "RSS"
    },
    {
      "source": "CNBC-World",
      "headline": "India flags slower growth, wider deficit as Iran war raises the stakes for New Delhi",
      "summary": "India warns growth may slow as the Iran conflict pushes up energy costs, widens deficits, and strains supply chains.",
      "url": "https://www.cnbc.com/2026/03/30/india-flags-slower-growth-wider-deficit-iran-war.html",
      "datetime": 1774850914,
      "related": "RSS"
    },
    {
      "source": "CNBC-Top",
      "headline": "Eli Lilly reaches $2.75 billion deal with Insilico to bring AI-developed drugs to the global market",
      "summary": "U.S. pharmaceutical giant Eli Lilly will give Hong Kong-listed Insilico $115 million upfront to bring some of its AI-discovered drugs to the global market.",
      "url": "https://www.cnbc.com/2026/03/29/eli-lilly-reaches-deal-to-bring-ai-developed-drugs-to-global-market.html",
      "datetime": 1774848902,
      "related": "RSS"
    },
    {
      "source": "CNBC-World",
      "headline": "CNBC Daily Open: Trump's 'favorite thing' is Iranian oil",
      "summary": "President Trump's tough rhetoric and a build-up of ground troops raise escalation fears and drive risk-averse trade across global markets.",
      "url": "https://www.cnbc.com/2026/03/30/cnbc-daily-open-trumps-favorite-thing-is-iranian-oil.html",
      "datetime": 1774848752,
      "related": "RSS"
    },
    {
      "source": "CNBC-World",
      "headline": "Pakistan prepared to host U.S.-Iran talks in 'coming days' as Trump weighs deploying ground troops",
      "summary": "Foreign ministers of Pakistan, Saudi Arabia, Turkey and Egypt all arrived in Islamabad to discuss the evolving regional situation in the Middle East.",
      "url": "https://www.cnbc.com/2026/03/29/bahrain-aluminum-giant-says-iranian-attack-targeted-its-facilit.html",
      "datetime": 1774821575,
      "related": "RSS"
    },
    {
      "source": "CNBC-Top",
      "headline": "The problem for investors: We don't know how Trump wants the Iran war to end",
      "summary": "In his Sunday column for Investing Club subscribers, Jim Cramer argues that the S&P 500 is likely to see further declines during the Iran war.",
      "url": "https://www.cnbc.com/2026/03/29/the-problem-for-investors-we-dont-know-how-trump-wants-the-iran-war-to-end.html",
      "datetime": 1774818209,
      "related": "RSS"
    },
    {
      "source": "CNBC-Top",
      "headline": "Meta's court losses spell potential trouble for AI research, consumer safety",
      "summary": "Meta's two courtroom defeats centered on different cases but both involved allegations that the company knew about its products' harms.",
      "url": "https://www.cnbc.com/2026/03/29/metas-court-losses-spell-trouble-for-ai-research-consumer-safety.html",
      "datetime": 1774804502,
      "related": "RSS"
    },
    {
      "source": "CNBC-Top",
      "headline": "Back-up care benefits at work go beyond kids, aging parents as more employers pay for pets",
      "summary": "Companies are expanding employee benefits to cover a wide variety of caregiving needs, including back-up care for children, aging parents, and pets.",
      "url": "https://www.cnbc.com/2026/03/29/backup-care-benefits-employees-kids-seniors-pets.html",
      "datetime": 1774792268,
      "related": "RSS"
    },
    {
      "source": "CNBC-Top",
      "headline": "Trump ban on investor homebuying may come at cost of a bigger real estate deal",
      "summary": "President Trump's plan to ban big investors from home ownership may not be the key to reviving the American Dream in affordable housing legislation.",
      "url": "https://www.cnbc.com/2026/03/29/affordable-housing-trump-ban-investor-home-buying-real-estate.html",
      "datetime": 1774791821,
      "related": "RSS"
    },
    {
      "source": "CNBC-Top",
      "headline": "I've studied over 200 kids. Here's the No. 1 skill parents are forgetting to teach kids today",
      "summary": "Parents today try to raise their children for good grades and high achievement. But that's not what we should be focusing on, says child psychologist Reem Raouda, who has studied over 200 kids. She shares the most important skill parents are forgetting to teach today.",
      "url": "https://www.cnbc.com/2026/03/29/ive-studied-over-200-kids-the-no-1-skill-parents-are-forgetting-to-teach-kids-today.html",
      "datetime": 1774788946,
      "related": "RSS"
    },
    {
      "source": "CNBC-Top",
      "headline": "Analysis: A new oil shock is building. The next few weeks of war will be decisive for the economy.",
      "summary": "Energy markets are starting to reflect the growing risk of physical supply disruptions.",
      "url": "https://www.cnbc.com/2026/03/28/oil-gas-prices-iran-war-hormuz.html",
      "datetime": 1774788666,
      "related": "RSS"
    },
    {
      "source": "CNBC-Top",
      "headline": "Logan Paul sold a Pokémon card for more than $16 million. Here's why investors are watching",
      "summary": "Some rare Pokémon cards are fetching huge prices and yielding better returns than the S&P 500.",
      "url": "https://www.cnbc.com/2026/03/29/pokemon-card-values-rise-logan-paul-pikachu-auction.html",
      "datetime": 1774785601,
      "related": "RSS"
    },
    {
      "source": "CNBC-World",
      "headline": "Global week ahead: Why emergency G7 meetings are not working",
      "summary": "Finance and energy ministers, as well as central bank governors from the G7 nations prepare for talks on Iran.",
      "url": "https://www.cnbc.com/2026/03/29/global-week-ahead-why-emergency-g7-meetings-are-not-working.html",
      "datetime": 1774760401,
      "related": "RSS"
    }
  ]
}